mtge/__init__.py
mtge/libxux64.so
mtge/mtge_calc.py
mtge/xux64.py
mtge-0.1.3.dist-info/METADATA
mtge-0.1.3.dist-info/WHEEL
mtge-0.1.3.dist-info/top_level.txt
mtge-0.1.3.dist-info/RECORD
