Metadata-Version: 2.4
Name: mtge
Version: 0.1.3
Summary: Mortgage Cashflow Calculator
Author: Beyondbond
Author-email: info@beyondbond.com
Classifier: Programming Language :: Python :: 3
Classifier: Operating System :: OS Independent
Requires-Python: >=3.8
Dynamic: author
Dynamic: author-email
Dynamic: classifier
Dynamic: description
Dynamic: description-content-type
Dynamic: requires-python
Dynamic: summary
